{
  "timestamp": "2016-01-20 04:03:50.433",
  "args": [
    "--upload"
  ],
  "host": "ip-10-226-23-227",
  "uuid": "25DE3fs9G7",
  "uploads": [
    {
      "tag": "dslink-dart-wemo",
      "source": "files/dslink-dart-wemo.zip",
      "target": "files/dslink-dart-wemo.zip",
      "revision": "bdac2ae7e7eb382b4656f4255d7afa53ef490b61"
    },
    {
      "tag": "meta.history",
      "source": "data/history.json",
      "target": "history.json",
      "revision": "25DE3fs9G7"
    },
    {
      "tag": "meta.revisions",
      "source": "data/revs.json",
      "target": "revs.json",
      "revision": "25DE3fs9G7"
    },
    {
      "tag": "meta.links",
      "source": "links.json",
      "target": "links.json",
      "revision": "25DE3fs9G7"
    },
    {
      "tag": "meta.updated",
      "source": "data/updated.json",
      "target": "updated.json",
      "revision": "25DE3fs9G7"
    }
  ],
  "built": [
    "WeMo"
  ]
}
