{
  "timestamp": "2020-05-22 00:00:35.302197",
  "args": [
    "--upload"
  ],
  "host": "sparky",
  "uuid": "NTlsZUHsmn",
  "uploads": [
    {
      "tag": "meta.history",
      "source": "data/history.json",
      "target": "history.json",
      "revision": "NTlsZUHsmn"
    },
    {
      "tag": "meta.revisions",
      "source": "data/revs.json",
      "target": "revs.json",
      "revision": "NTlsZUHsmn"
    },
    {
      "tag": "meta.links",
      "source": "links.json",
      "target": "links.json",
      "revision": "NTlsZUHsmn"
    },
    {
      "tag": "meta.updated",
      "source": "data/updated.json",
      "target": "updated.json",
      "revision": "NTlsZUHsmn"
    }
  ],
  "built": []
}
