{
  "timestamp": "2021-10-20 00:00:34.858444",
  "args": [
    "--upload"
  ],
  "host": "sparky",
  "uuid": "xHNa0l86K3",
  "uploads": [
    {
      "tag": "meta.history",
      "source": "data/history.json",
      "target": "history.json",
      "revision": "xHNa0l86K3"
    },
    {
      "tag": "meta.revisions",
      "source": "data/revs.json",
      "target": "revs.json",
      "revision": "xHNa0l86K3"
    },
    {
      "tag": "meta.links",
      "source": "links.json",
      "target": "links.json",
      "revision": "xHNa0l86K3"
    },
    {
      "tag": "meta.updated",
      "source": "data/updated.json",
      "target": "updated.json",
      "revision": "xHNa0l86K3"
    }
  ],
  "built": []
}
